imgui/__init__.py
imgui/_compat.py
imgui/ansifeed.pxd
imgui/cimgui.pxd
imgui/common.pyx
imgui/core.cpp
imgui/core.cpython-38-x86_64-linux-gnu.so
imgui/core.h
imgui/core.pxd
imgui/core.pyx
imgui/enums.pxd
imgui/enums_internal.pxd
imgui/extra.py
imgui/internal.cpp
imgui/internal.cpython-38-x86_64-linux-gnu.so
imgui/internal.h
imgui/internal.pxd
imgui/internal.pyx
imgui/integrations/__init__.py
imgui/integrations/base.py
imgui/integrations/cocos2d.py
imgui/integrations/glfw.py
imgui/integrations/glumpy.py
imgui/integrations/opengl.py
imgui/integrations/pygame.py
imgui/integrations/pyglet.py
imgui/integrations/sdl2.py
pyimgui_wheels-2.0.1.dist-info/LICENSE
pyimgui_wheels-2.0.1.dist-info/METADATA
pyimgui_wheels-2.0.1.dist-info/WHEEL
pyimgui_wheels-2.0.1.dist-info/top_level.txt
pyimgui_wheels-2.0.1.dist-info/RECORD
