Metadata-Version: 2.1
Name: pyimgui-wheels
Version: 2.0.1
Summary: Cython-based Python bindings for dear imgui
Home-page: https://github.com/swistakm/pyimgui
Author: Michał Jaworski
Author-email: swistakm@gmail.com
License: BSD
Platform: UNKNOWN
Classifier: Intended Audience :: Developers
Classifier: License :: OSI Approved :: BSD License
Classifier: Programming Language :: Cython
Classifier: Programming Language :: Python :: 2
Classifier: Programming Language :: Python :: 2.7
Classifier: Programming Language :: Python :: 3
Classifier: Programming Language :: Python :: 3.3
Classifier: Programming Language :: Python :: 3.4
Classifier: Programming Language :: Python :: 3.5
Classifier: Programming Language :: Python :: 3.6
Classifier: Programming Language :: Python :: Implementation :: CPython
Classifier: Programming Language :: Cython
Classifier: Operating System :: MacOS :: MacOS X
Classifier: Operating System :: POSIX :: Linux
Classifier: Operating System :: Microsoft :: Windows
Classifier: Topic :: Games/Entertainment
Provides-Extra: cython
Requires-Dist: Cython (<0.30,>=0.24) ; extra == 'cython'
Provides-Extra: cocos2d
Requires-Dist: PyOpenGL ; extra == 'cocos2d'
Requires-Dist: cocos2d ; extra == 'cocos2d'
Requires-Dist: pyglet (>=1.5.6) ; (sys_platform == "darwin") and extra == 'cocos2d'
Provides-Extra: full
Requires-Dist: Cython (<0.30,>=0.24) ; extra == 'full'
Requires-Dist: PyOpenGL ; extra == 'full'
Requires-Dist: PySDL2 ; extra == 'full'
Requires-Dist: cocos2d ; extra == 'full'
Requires-Dist: glfw ; extra == 'full'
Requires-Dist: pygame ; extra == 'full'
Requires-Dist: pyglet ; (sys_platform != "darwin") and extra == 'full'
Requires-Dist: pyglet (>=1.5.6) ; (sys_platform == "darwin") and extra == 'full'
Provides-Extra: glfw
Requires-Dist: PyOpenGL ; extra == 'glfw'
Requires-Dist: glfw ; extra == 'glfw'
Provides-Extra: opengl
Requires-Dist: PyOpenGL ; extra == 'opengl'
Provides-Extra: pygame
Requires-Dist: PyOpenGL ; extra == 'pygame'
Requires-Dist: pygame ; extra == 'pygame'
Provides-Extra: pyglet
Requires-Dist: PyOpenGL ; extra == 'pyglet'
Requires-Dist: pyglet ; (sys_platform != "darwin") and extra == 'pyglet'
Requires-Dist: pyglet (>=1.5.6) ; (sys_platform == "darwin") and extra == 'pyglet'
Provides-Extra: sdl2
Requires-Dist: PyOpenGL ; extra == 'sdl2'
Requires-Dist: PySDL2 ; extra == 'sdl2'
